setup.py
cloudooo/CHANGES.txt
cloudooo/NEWS
cloudooo/README.txt
cloudooo/__init__.py
cloudooo/file.py
cloudooo/manager.py
cloudooo/paster_application.py
cloudooo/wsgixmlrpcapplication.py
cloudooo.egg-info/PKG-INFO
cloudooo.egg-info/SOURCES.txt
cloudooo.egg-info/dependency_links.txt
cloudooo.egg-info/entry_points.txt
cloudooo.egg-info/not-zip-safe
cloudooo.egg-info/requires.txt
cloudooo.egg-info/top_level.txt
cloudooo/bin/__init__.py
cloudooo/bin/cloudooo_tester.py
cloudooo/bin/echo_cloudooo_conf.py
cloudooo/handler/__init__.py
cloudooo/handler/tests/__init__.py
cloudooo/handler/tests/handlerTestCase.py
cloudooo/handler/tests/runHandlerUnitTest.py
cloudooo/interfaces/__init__.py
cloudooo/interfaces/application.py
cloudooo/interfaces/file.py
cloudooo/interfaces/filter.py
cloudooo/interfaces/granulate.py
cloudooo/interfaces/handler.py
cloudooo/interfaces/lockable.py
cloudooo/interfaces/manager.py
cloudooo/interfaces/mimemapper.py
cloudooo/interfaces/monitor.py
cloudooo/samples/cloudooo.conf
cloudooo/samples/cloudooo.conf.in
cloudooo/samples/rubyclient.rb
cloudooo/samples/sample.conf
cloudooo/utils/__init__.py
cloudooo/utils/mime.types
cloudooo/utils/utils.py