Metadata-Version: 1.0
Name: cloudooo
Version: 1.2.3
Summary: XML-RPC document conversion server
Home-page: https://svn.erp5.org/repos/public/erp5/trunk/utils/cloudooo
Author: Gabriel M. Monnerat
Author-email: gabriel@tiolive.com
License: GPLv3
Keywords: xmlrpc openoffice wsgi paste python
Platform: UNKNOWN
Classifier: Topic :: System :: Networking
Classifier: Topic :: System :: Operating System Kernels :: Linux
Classifier: Topic :: Internet :: WWW/HTTP :: WSGI
Classifier: Programming Language :: Python :: 2.6
Classifier: Natural Language :: English
Classifier: Framework :: Paste
